kovit_citers.cp36-win_amd64.pyd
kovit_cjson.cp36-win_amd64.pyd
kovit/__init__.py
kovit/bag.py
kovit/chain.py
kovit/iters.py
kovit/json.py
kovit/piters.py
kovit/pjson.py
kovit-0.1.19.4a1.dist-info/METADATA
kovit-0.1.19.4a1.dist-info/WHEEL
kovit-0.1.19.4a1.dist-info/top_level.txt
kovit-0.1.19.4a1.dist-info/RECORD
