Metadata-Version: 2.1
Name: kovit
Version: 0.1.19.4a1
Summary: Generic incrementally buildable Markov chains for text generation and other purposes.
Home-page: https://github.com/Teriks/kovit
Author: Teriks
Author-email: Teriks@users.noreply.github.com
License: BSD 3-Clause
Platform: UNKNOWN
Classifier: Development Status :: 3 - Alpha
Classifier: License :: OSI Approved :: BSD License
Classifier: Intended Audience :: Developers
Classifier: Natural Language :: English
Classifier: Operating System :: OS Independent
Classifier: Topic :: Software Development :: Libraries
Requires-Python: >=3.5
Requires-Dist: cffi
Requires-Dist: ijson
Requires-Dist: ujson
